torch_subpixel_crop/__init__.py
torch_subpixel_crop/dft_utils.py
torch_subpixel_crop/grid_sample_utils.py
torch_subpixel_crop/subpixel_crop_2d.py
torch_subpixel_crop/subpixel_crop_3d.py
torch_subpixel_crop-0.1.1.dist-info/METADATA
torch_subpixel_crop-0.1.1.dist-info/WHEEL
torch_subpixel_crop-0.1.1.dist-info/licenses/LICENSE
torch_subpixel_crop-0.1.1.dist-info/RECORD
