Metadata-Version: 2.4
Name: torch-subpixel-crop
Version: 0.1.1
Summary: Extract 2D/3D subimages with subpixel precision in PyTorch
Project-URL: homepage, https://github.com/alisterburt/torch-subimage
Project-URL: repository, https://github.com/alisterburt/torch-subimage
Author-email: Alister Burt <alisterburt@gmail.com>
License: BSD-3-Clause
License-File: LICENSE
Classifier: Development Status :: 3 - Alpha
Classifier: License :: OSI Approved :: BSD License
Classifier: Programming Language :: Python :: 3
Classifier: Programming Language :: Python :: 3.9
Classifier: Programming Language :: Python :: 3.10
Classifier: Programming Language :: Python :: 3.11
Classifier: Programming Language :: Python :: 3.12
Classifier: Typing :: Typed
Requires-Python: >=3.9
Requires-Dist: einops
Requires-Dist: numpy
Requires-Dist: torch
Requires-Dist: torch-fourier-shift
Requires-Dist: torch-grid-utils
Provides-Extra: dev
Requires-Dist: ipython; extra == 'dev'
Requires-Dist: mypy; extra == 'dev'
Requires-Dist: pdbpp; extra == 'dev'
Requires-Dist: pre-commit; extra == 'dev'
Requires-Dist: rich; extra == 'dev'
Requires-Dist: ruff; extra == 'dev'
Provides-Extra: test
Requires-Dist: pytest; extra == 'test'
Requires-Dist: pytest-cov; extra == 'test'
